danielchen_utils/__init__.py
danielchen_utils/http_requests.py
danielchen_utils/redis.py
danielchen_utils/upload.py
danielchen_utils/util.py
danielchen_utils/data/config.py
danielchen_utils/data/response_json.py
danielchen_utils-0.1.2.1.dist-info/METADATA
danielchen_utils-0.1.2.1.dist-info/WHEEL
danielchen_utils-0.1.2.1.dist-info/licenses/LICENSE
danielchen_utils-0.1.2.1.dist-info/RECORD
